[
  {
    "name": "Александр",
    "middle_name": "Сергеевич",
    "surname": "Черный",
    "school": "67 школа",
    "class": [
      "5 А",
      "5 Б",
      "6 Б",
      "7 В"
    ],
    "id": 1,
    "birth_day": "04.07.1978"
  },
  {
    "name": "Владимир",
    "middle_name": "Сергеевич",
    "surname": "Вышкин",
    "school": "12 гимназия",
    "class": [
      "6 А",
      "7 В"
    ],
    "id": 2,
    "birth_day": "24.12.1982"
  },
  {
    "name": "Петр",
    "middle_name": "Иванович",
    "surname": "Кошкин",
    "school": "12 гимназия",
    "class": [
      "7 А",
      "7 Б",
      "7 Г",
      "7 В"
    ],
    "id": 3,
    "birth_day": "14.02.1980"
  },
  {
    "name": "Александр",
    "middle_name": "Сергеевич",
    "surname": "Белый",
    "school": "67 шк",
    "class": [
      "6 Г",
      "8 А",
      "8 Б",
      "8 Г",
      "8 В"
    ],
    "id": 4,
    "birth_day": "14.02.1980"
  },
  {
    "name": "Иван",
    "middle_name": "Васильевич",
    "surname": "Новый",
    "school": "67 шк",
    "class": [],
    "id": 5,
    "birth_day": "16.07.1984"
  },
  {
    "name": "Ирина",
    "middle_name": "Владимировна",
    "surname": "Турцева",
    "school": "67 школа",
    "class": [
      "1 А",
      "4 Б",
      "10 А",
      "10 А"
    ],
    "id": 6,
    "birth_day": "02.09.1950"
  }
]